lightkg/__init__.py
lightkg/base/__init__.py
lightkg/base/config.py
lightkg/base/model.py
lightkg/base/module.py
lightkg/base/tool.py
lightkg/common/__init__.py
lightkg/common/entity.py
lightkg/common/relation.py
lightkg/ede/__init__.py
lightkg/ede/srl/__init__.py
lightkg/ede/srl/config.py
lightkg/ede/srl/model.py
lightkg/ede/srl/module.py
lightkg/ede/srl/tool.py
lightkg/ede/srl/utils/__init__.py
lightkg/ede/srl/utils/convert.py
lightkg/ere/__init__.py
lightkg/ere/re/__init__.py
lightkg/ere/re/config.py
lightkg/ere/re/model.py
lightkg/ere/re/module.py
lightkg/ere/re/tool.py
lightkg/ere/re/utils/__init__.py
lightkg/ere/re/utils/dataset.py
lightkg/ere/re/utils/preprocess.py
lightkg/erl/__init__.py
lightkg/erl/ner/__init__.py
lightkg/erl/ner/config.py
lightkg/erl/ner/model.py
lightkg/erl/ner/module.py
lightkg/erl/ner/tool.py
lightkg/erl/ner/utils/__init__.py
lightkg/erl/ner/utils/convert.py
lightkg/kr/__init__.py
lightkg/krl/__init__.py
lightkg/krl/config.py
lightkg/krl/module.py
lightkg/krl/tool.py
lightkg/krl/models/__init__.py
lightkg/krl/models/transE/__init__.py
lightkg/krl/models/transE/config.py
lightkg/krl/models/transE/model.py
lightkg/krl/utils/__init__.py
lightkg/krl/utils/get_neg_batch.py
lightkg/krl/utils/score_func.py
lightkg/ksq/__init__.py
lightkg/utils/__init__.py
lightkg/utils/learning.py
lightkg/utils/log.py
lightKG-0.1.0.3.dist-info/LICENSE
lightKG-0.1.0.3.dist-info/METADATA
lightKG-0.1.0.3.dist-info/WHEEL
lightKG-0.1.0.3.dist-info/top_level.txt
lightKG-0.1.0.3.dist-info/RECORD
